cnri_json_streaming/__init__.py
cnri_json_streaming/jsonparse.py
cnri_json_streaming/jsonreader.py
cnri_json_streaming/py.typed
cnri_json_streaming-1.0.0.dist-info/METADATA
cnri_json_streaming-1.0.0.dist-info/WHEEL
cnri_json_streaming-1.0.0.dist-info/licenses/LICENSE.txt
cnri_json_streaming-1.0.0.dist-info/RECORD
