Metadata-Version: 2.4
Name: cnri-json-streaming
Version: 1.0.0
Summary: Streaming JSON parser
Project-URL: homepage, https://www.cordra.org
Project-URL: source, https://gitlab.com/cnri/cnri-json-streaming-python
Project-URL: documentation, https://www.cordra.org/doip/cnri-json-streaming-python/api-docs/index.html
Author-email: CNRI <support@cordra.org>
License-File: LICENSE.txt
Keywords: json,parse,parser,streaming
Classifier: Operating System :: OS Independent
Classifier: Programming Language :: Python :: 3
Classifier: Topic :: File Formats :: JSON
Classifier: Typing :: Typed
Requires-Python: >=3.12
Requires-Dist: ijson~=3.3
Provides-Extra: docs
Requires-Dist: myst-parser~=4.0; extra == 'docs'
Requires-Dist: sphinx-autobuild~=2025.8; extra == 'docs'
Requires-Dist: sphinx-rtd-theme~=3.0; extra == 'docs'
Requires-Dist: sphinx~=8.2; extra == 'docs'
Provides-Extra: test
Requires-Dist: pytest~=8.2; extra == 'test'
